stelvio/__init__.py
stelvio/_suppress_grpc.py
stelvio/app.py
stelvio/command_run.py
stelvio/component.py
stelvio/config.py
stelvio/context.py
stelvio/dns.py
stelvio/exceptions.py
stelvio/git.py
stelvio/home.py
stelvio/link.py
stelvio/project.py
stelvio/pulumi.py
stelvio/rich_deployment_handler.py
stelvio/state_ops.py
stelvio/aws/__init__.py
stelvio/aws/acm.py
stelvio/aws/cors.py
stelvio/aws/cron.py
stelvio/aws/dns.py
stelvio/aws/dynamo_db.py
stelvio/aws/email.py
stelvio/aws/home.py
stelvio/aws/layer.py
stelvio/aws/permission.py
stelvio/aws/queue.py
stelvio/aws/topic.py
stelvio/aws/types.py
stelvio/aws/_packaging/__init__.py
stelvio/aws/_packaging/dependencies.py
stelvio/aws/api_gateway/__init__.py
stelvio/aws/api_gateway/api.py
stelvio/aws/api_gateway/config.py
stelvio/aws/api_gateway/constants.py
stelvio/aws/api_gateway/cors.py
stelvio/aws/api_gateway/deployment.py
stelvio/aws/api_gateway/iam.py
stelvio/aws/api_gateway/routing.py
stelvio/aws/cloudfront/__init__.py
stelvio/aws/cloudfront/cloudfront.py
stelvio/aws/cloudfront/dtos.py
stelvio/aws/cloudfront/js.py
stelvio/aws/cloudfront/router.py
stelvio/aws/cloudfront/origins/__init__.py
stelvio/aws/cloudfront/origins/base.py
stelvio/aws/cloudfront/origins/decorators.py
stelvio/aws/cloudfront/origins/registry.py
stelvio/aws/cloudfront/origins/components/__init__.py
stelvio/aws/cloudfront/origins/components/api_gateway.py
stelvio/aws/cloudfront/origins/components/lambda_function.py
stelvio/aws/cloudfront/origins/components/s3.py
stelvio/aws/cloudfront/origins/components/url.py
stelvio/aws/function/__init__.py
stelvio/aws/function/config.py
stelvio/aws/function/constants.py
stelvio/aws/function/dependencies.py
stelvio/aws/function/function.py
stelvio/aws/function/iam.py
stelvio/aws/function/naming.py
stelvio/aws/function/packaging.py
stelvio/aws/function/resources_codegen.py
stelvio/aws/s3/__init__.py
stelvio/aws/s3/s3.py
stelvio/aws/s3/s3_static_website.py
stelvio/bridge/__init__.py
stelvio/bridge/_chunking.py
stelvio-0.7.0b1.dist-info/METADATA
stelvio-0.7.0b1.dist-info/WHEEL
stelvio-0.7.0b1.dist-info/entry_points.txt
stelvio-0.7.0b1.dist-info/licenses/LICENSE
stelvio-0.7.0b1.dist-info/RECORD
