Metadata-Version: 2.4
Name: stelvio
Version: 0.7.0b1
Summary: AWS for Python devs made simple.
Project-URL: homepage, https://stelvio.dev/
Project-URL: repository, https://github.com/stelviodev/stelvio
Project-URL: documentation, https://stelvio.dev/docs/
Project-URL: Bug Tracker, https://github.com/stelviodev/stelvio/issues
Author-email: Michal Martinka <michal@stelvio.dev>, Bas Steins <bas@stelvio.dev>
Maintainer-email: Michal <michal@stelvio.dev>, Bas Steins <bas@stelvio.dev>
License: Apache-2.0
License-File: LICENSE
Keywords: aws,cloudflare,infrastructure
Classifier: Development Status :: 4 - Beta
Classifier: Intended Audience :: Developers
Classifier: License :: OSI Approved :: Apache Software License
Classifier: Programming Language :: Python :: 3
Classifier: Programming Language :: Python :: 3.12
Classifier: Programming Language :: Python :: 3.13
Classifier: Topic :: Software Development :: Libraries :: Python Modules
Classifier: Topic :: System :: Systems Administration
Requires-Python: >=3.12
Requires-Dist: appdirs<2,>=1.0
Requires-Dist: awslambdaric<4,>=3.0
Requires-Dist: boto3<2,>=1.0
Requires-Dist: click<9,>=8.0
Requires-Dist: pulumi-aws==7.16.0
Requires-Dist: pulumi-cloudflare==6.12.0
Requires-Dist: pulumi==3.216.0
Requires-Dist: requests<3,>=2.0
Requires-Dist: rich<15,>=14.0
Requires-Dist: websockets<17,>=15.0
